TrentUPackage/PdfScraper.py
TrentUPackage/WebsiteScraper.py
TrentUPackage/bot.py
TrentUPackage/test.py
TrentUPackage-0.0.4.dist-info/METADATA
TrentUPackage-0.0.4.dist-info/WHEEL
TrentUPackage-0.0.4.dist-info/entry_points.txt
TrentUPackage-0.0.4.dist-info/top_level.txt
TrentUPackage-0.0.4.dist-info/RECORD
